<beans xmlns="http://www.springframework.org/schema/beans"
	xmlns:xsi="http://www.w3.org/2001/XMLSchema-instance"
	xmlns:util="http://www.springframework.org/schema/util"
	xmlns:context="http://www.springframework.org/schema/context"
	xsi:schemaLocation="http://www.springframework.org/schema/beans
http://www.springframework.org/schema/beans/spring-beans-3.0.xsd
http://www.springframework.org/schema/util http://www.springframework.org/schema/util/spring-util-3.0.xsd
http://www.springframework.org/schema/context http://www.springframework.org/schema/context/spring-context-3.0.xsd">

	<bean id="mailSender" class="org.springframework.mail.javamail.JavaMailSenderImpl">
		<property name="host" value="smtp.gmail.com" />
		<property name="port" value="587" />
		<property name="username" value="rajeshjreddy@gmail.com" />
		<property name="password" value="" />

		<property name="javaMailProperties">
			<props>
				<prop key="mail.smtp.auth">true</prop>
				<prop key="mail.smtp.starttls.enable">true</prop>
			</props>
		</property>
	</bean>

	<bean id="emailSource"
		class="org.springframework.context.support.ResourceBundleMessageSource">
		<property name="basename" value="com/bank/resources/email" />
	</bean>
	<util:properties id="views" location="classpath:com/bank/resources/views.properties"></util:properties>
 

</beans>